bluer_south/README.py
bluer_south/__init__.py
bluer_south/__main__.py
bluer_south/content.py
bluer_south/host.py
bluer_south/logger.py
bluer_south/urls.py
bluer_south/.abcli/abcli.sh
bluer_south/.abcli/actions.sh
bluer_south/.abcli/aka.sh
bluer_south/.abcli/alias.sh
bluer_south/.abcli/bluer_south.sh
bluer_south/.abcli/tests/README.sh
bluer_south/.abcli/tests/help.sh
bluer_south/.abcli/tests/version.sh
bluer_south/help/__init__.py
bluer_south/help/__main__.py
bluer_south/help/functions.py
bluer_south-4.129.1.dist-info/licenses/LICENSE
bluer_south-4.129.1.dist-info/METADATA
bluer_south-4.129.1.dist-info/WHEEL
bluer_south-4.129.1.dist-info/top_level.txt
bluer_south-4.129.1.dist-info/RECORD
