Metadata-Version: 2.4
Name: bluer_south
Version: 4.129.1
Summary: 🌀 AI for Global South: Free from Big Tech.
Home-page: https://github.com/kamangir/bluer-south
Author: Arash Abadpour (Kamangir)
Author-email: arash.abadpour@gmail.com
License: CC0-1.0
Classifier: Programming Language :: Python :: 3
Classifier: Programming Language :: Unix Shell
Classifier: Operating System :: OS Independent
License-File: LICENSE
Requires-Dist: bluer_ai
Requires-Dist: abadpour
Requires-Dist: bluer_academy
Requires-Dist: bluer_agent
Requires-Dist: bluer_algo
Requires-Dist: bluer_flow
Requires-Dist: bluer_geo
Requires-Dist: bluer_journal
Requires-Dist: bluer_plugin
Requires-Dist: bluer_sandbox
Requires-Dist: bluer_sbc
Requires-Dist: bluer_ugv
Requires-Dist: gizai
Requires-Dist: vancouver_watching
Dynamic: author
Dynamic: author-email
Dynamic: classifier
Dynamic: description
Dynamic: description-content-type
Dynamic: home-page
Dynamic: license
Dynamic: license-file
Dynamic: requires-dist
Dynamic: summary
